easimpconf/VERSION
easimpconf/__init__.py
easimpconf/_config.py
easimpconf/_errors.py
easimpconf/_spec.py
easimpconf/_utils.py
easimpconf-0.2.2.dist-info/LICENSE.txt
easimpconf-0.2.2.dist-info/METADATA
easimpconf-0.2.2.dist-info/WHEEL
easimpconf-0.2.2.dist-info/top_level.txt
easimpconf-0.2.2.dist-info/RECORD
